athenapi/__init__.py
athenapi/conversation_lite.py
athenapi/mac_board.py
athenapi/microphone.py
athenapi/rpi0_iqaudio_board.py
athenapi/rpi_button.py
athenapi/rpi_led.py
athenapi/rpi_zero_camera.py
athenapi/speaker.py
athenapi/assets/beep-down.wav
athenapi/assets/beep-up.wav
athenapi/assets/camera.mp3
athenapi-0.1.4.dist-info/METADATA
athenapi-0.1.4.dist-info/WHEEL
athenapi-0.1.4.dist-info/entry_points.txt
athenapi-0.1.4.dist-info/top_level.txt
athenapi-0.1.4.dist-info/RECORD
